swift_book_pdf/__init__.py
swift_book_pdf/assets/Swift_logo_color.png
swift_book_pdf/assets/Swift_logo_white.png
swift_book_pdf/assets/chapter-icon.png
swift_book_pdf/assets/chapter-icon~dark.png
swift_book_pdf/blocks.py
swift_book_pdf/book.py
swift_book_pdf/chapters.py
swift_book_pdf/cli.py
swift_book_pdf/colors.py
swift_book_pdf/config.py
swift_book_pdf/contents.py
swift_book_pdf/doc.py
swift_book_pdf/doc_tags.py
swift_book_pdf/files.py
swift_book_pdf/fonts.py
swift_book_pdf/latex.py
swift_book_pdf/latex_helpers.py
swift_book_pdf/log.py
swift_book_pdf/markdown_helpers.py
swift_book_pdf/pdf.py
swift_book_pdf/preamble.py
swift_book_pdf/schema.py
swift_book_pdf/styles.py
swift_book_pdf/toc.py
swift_book_pdf-2.0.0.dist-info/METADATA
swift_book_pdf-2.0.0.dist-info/WHEEL
swift_book_pdf-2.0.0.dist-info/entry_points.txt
swift_book_pdf-2.0.0.dist-info/licenses/LICENSE
swift_book_pdf-2.0.0.dist-info/RECORD
