Metadata-Version: 2.4
Name: swift-book-pdf
Version: 2.0.0
Summary: A tool to generate a PDF version of The Swift Programming Language book.
License-Expression: Apache-2.0
License-File: LICENSE
Keywords: swift,book,pdf
Author: Evangelos Kassos
Author-email: github@evangeloskassos.com
Requires-Python: >=3.10
Classifier: Programming Language :: Python :: 3
Classifier: Programming Language :: Python :: 3.10
Classifier: Programming Language :: Python :: 3.11
Classifier: Programming Language :: Python :: 3.12
Classifier: Programming Language :: Python :: 3.13
Classifier: Programming Language :: Python :: 3.14
Requires-Dist: click (>=8.1.8,<9.0.0)
Requires-Dist: latexminted (>=0.5.0,<0.6.0)
Requires-Dist: pydantic (>=2.10.6,<3.0.0)
Requires-Dist: pygments (>=2.9.0,<3.0.0)
Requires-Dist: tqdm (>=4.67.1,<5.0.0)
Project-URL: Documentation, https://github.com/ekassos/swift-book-pdf/wiki
Project-URL: Repository, https://github.com/ekassos/swift-book-pdf.git
Project-URL: changelog, https://github.com/ekassos/swift-book-pdf/blob/main/CHANGELOG.md
Project-URL: issues, https://github.com/ekassos/swift-book-pdf/issues
Project-URL: releasenotes, https://github.com/ekassos/swift-book-pdf/releases
